td_client-1.6.0.dist-info/licenses/LICENSE
tdclient/__init__.py
tdclient/api.py
tdclient/bulk_import_api.py
tdclient/bulk_import_model.py
tdclient/client.py
tdclient/connection.py
tdclient/connector_api.py
tdclient/cursor.py
tdclient/database_api.py
tdclient/database_model.py
tdclient/errors.py
tdclient/export_api.py
tdclient/import_api.py
tdclient/job_api.py
tdclient/job_model.py
tdclient/model.py
tdclient/models.py
tdclient/py.typed
tdclient/result_api.py
tdclient/result_model.py
tdclient/schedule_api.py
tdclient/schedule_model.py
tdclient/server_status_api.py
tdclient/table_api.py
tdclient/table_model.py
tdclient/types.py
tdclient/user_api.py
tdclient/user_model.py
tdclient/util.py
tdclient/version.py
td_client-1.6.0.dist-info/METADATA
td_client-1.6.0.dist-info/WHEEL
td_client-1.6.0.dist-info/top_level.txt
td_client-1.6.0.dist-info/RECORD
