Metadata-Version: 2.4
Name: td-client
Version: 1.6.0
Summary: Treasure Data API library for Python
Author-email: "Treasure Data, Inc." <support@treasure-data.com>
License: Apache Software License
Project-URL: homepage, http://treasuredata.com/
Classifier: Development Status :: 4 - Beta
Classifier: Environment :: Web Environment
Classifier: Intended Audience :: Developers
Classifier: License :: OSI Approved :: Apache Software License
Classifier: Operating System :: OS Independent
Classifier: Topic :: Internet
Classifier: Programming Language :: Python :: 3.10
Classifier: Programming Language :: Python :: 3.11
Classifier: Programming Language :: Python :: 3.12
Classifier: Programming Language :: Python :: 3.13
Classifier: Programming Language :: Python :: 3.14
Classifier: Programming Language :: Python :: Implementation :: CPython
Classifier: Programming Language :: Python :: Implementation :: PyPy
Requires-Python: >=3.10
License-File: LICENSE
Requires-Dist: python-dateutil
Requires-Dist: msgpack>=0.6.2
Requires-Dist: urllib3
Provides-Extra: docs
Requires-Dist: sphinx; extra == "docs"
Requires-Dist: sphinx_rtd_theme; extra == "docs"
Provides-Extra: test
Requires-Dist: coverage[toml]; extra == "test"
Requires-Dist: pytest>=8.3; extra == "test"
Requires-Dist: coveralls<5.0,>=1.1; extra == "test"
Requires-Dist: pyyaml; extra == "test"
Dynamic: license-file
